MANIFEST.in
README.md
setup.py
hclient/ClientIde.py
hclient/LICENSE
hclient/README.md
hclient/__init__.py
hclient/client.py
hclient/utils.py
hclient/base/BaseClient.py
hclient/base/Cookies.py
hclient/base/Headers.py
hclient/base/Request.py
hclient/base/RequestGroup.py
hclient/base/Response.py
hclient/base/Site.py
hclient/base/__init__.py
hclient/formatters/Formatter.py
hclient/formatters/JsonFormatter.py
hclient/formatters/JsonParser.py
hclient/formatters/Parser.py
hclient/formatters/__init__.py
hclient/protocols/HttpRequest.py
hclient/protocols/ServiceResponse.py
hclient/protocols/__init__.py
hclient/transports/CurlTransport.py
hclient/transports/SocketTransport.py
hclient/transports/Transport.py
hclient/transports/UrllibTransport.py
hclient/transports/__init__.py
hehey_hclient.egg-info/PKG-INFO
hehey_hclient.egg-info/SOURCES.txt
hehey_hclient.egg-info/dependency_links.txt
hehey_hclient.egg-info/top_level.txt