Metadata-Version: 2.1
Name: hehey-hclient
Version: 1.3.8
Summary: hehey-hclient 是一个python 客户端请求工具组件,常用于接口的调用
Home-page: https://gitee.com/chinahehe/hehey-hclient
Author: 13564768842
Author-email: chinabluexfw@163.com
License: UNKNOWN
Platform: UNKNOWN
